crawler/__init__.py
crawler/app.py
crawler/endpoints.py
crawler/settings.py
scrapymims/__init__.py
scrapymims/app.py
scrapymims/endpoints.py
scrapymims/items.py
scrapymims/middlewares.py
scrapymims/pipelines.py
scrapymims/settings.py
scrapymims/spiders/__init__.py
scrapymims/spiders/images_spider.py
crawler_test-0.1.1.dist-info/METADATA
crawler_test-0.1.1.dist-info/WHEEL
crawler_test-0.1.1.dist-info/top_level.txt
crawler_test-0.1.1.dist-info/RECORD
