Metadata-Version: 2.1
Name: crawler-test
Version: 0.1.1
Summary: This is a web application that extracts images URLs from web pages.
Home-page: UNKNOWN
Author: Amal Boukhdhir
Author-email: boukhdhiramal@yahoo.fr
License: MIT
Platform: UNKNOWN
Requires-Dist: Scrapy
Requires-Dist: scrapyd
Requires-Dist: Flask
